MANIFEST.in
README.rst
requirements.txt
setup.py
random_episode/__init__.py
random_episode/config.py
random_episode/exceptions.py
random_episode/fs.py
random_episode/main.py
random_episode/management.py
random_episode/players.py
random_episode.egg-info/PKG-INFO
random_episode.egg-info/SOURCES.txt
random_episode.egg-info/dependency_links.txt
random_episode.egg-info/not-zip-safe
random_episode.egg-info/pbr.json
random_episode.egg-info/requires.txt
random_episode.egg-info/top_level.txt
scripts/random-episode