Metadata-Version: 1.1
Name: random-episode
Version: 0.1.1
Summary: Package description
